piper_sdk/__init__.py
piper_sdk/can_activate.sh
piper_sdk/can_config.sh
piper_sdk/can_find_and_config.sh
piper_sdk/can_muti_activate.sh
piper_sdk/find_all_can_port.sh
piper_sdk/version.py
piper_sdk/demo/__init__.py
piper_sdk/demo/detect_arm.MD
piper_sdk/demo/detect_arm.py
piper_sdk/demo/manage_vcan.py
piper_sdk/demo/V2/README.MD
piper_sdk/demo/V2/V2_piper_ctrl_joint_mit.py
piper_sdk/demo/V2/V2_piper_ctrl_motor_max_spd.py
piper_sdk/demo/V2/V2_piper_read_gripper_param_feedback.py
piper_sdk/demo/V2/V2_piper_set_gripper_param.py
piper_sdk/demo/V2/V2_piper_set_installation_pos.py
piper_sdk/demo/V2/__init__.py
piper_sdk/demo/V2/piper_ctrl_disable.py
piper_sdk/demo/V2/piper_ctrl_enable.py
piper_sdk/demo/V2/piper_ctrl_end_pose.py
piper_sdk/demo/V2/piper_ctrl_go_zero.py
piper_sdk/demo/V2/piper_ctrl_gripper.py
piper_sdk/demo/V2/piper_ctrl_joint.py
piper_sdk/demo/V2/piper_ctrl_line.py
piper_sdk/demo/V2/piper_ctrl_moveC.py
piper_sdk/demo/V2/piper_ctrl_reset.py
piper_sdk/demo/V2/piper_ctrl_stop.py
piper_sdk/demo/V2/piper_read_all_fps.py
piper_sdk/demo/V2/piper_read_arm_motor_max_acc_limit.py
piper_sdk/demo/V2/piper_read_arm_motor_max_angle_spd.py
piper_sdk/demo/V2/piper_read_crash_protectation.py
piper_sdk/demo/V2/piper_read_end_pose.py
piper_sdk/demo/V2/piper_read_firmware.py
piper_sdk/demo/V2/piper_read_fk.py
piper_sdk/demo/V2/piper_read_gripper_status.py
piper_sdk/demo/V2/piper_read_high_msg.py
piper_sdk/demo/V2/piper_read_joint_ctrl.py
piper_sdk/demo/V2/piper_read_joint_state.py
piper_sdk/demo/V2/piper_read_low_msg.py
piper_sdk/demo/V2/piper_read_mode_ctrl.py
piper_sdk/demo/V2/piper_read_mode_ctrl_canid_151.py
piper_sdk/demo/V2/piper_read_resp_instruction.py
piper_sdk/demo/V2/piper_read_status.py
piper_sdk/demo/V2/piper_read_tcp_pose.py
piper_sdk/demo/V2/piper_read_version.py
piper_sdk/demo/V2/piper_set_gripper_zero.py
piper_sdk/demo/V2/piper_set_init_default.py
piper_sdk/demo/V2/piper_set_joint_zero.py
piper_sdk/demo/V2/piper_set_load.py
piper_sdk-0.5.0.dist-info/LICENSE
piper_sdk-0.5.0.dist-info/METADATA
piper_sdk-0.5.0.dist-info/WHEEL
piper_sdk-0.5.0.dist-info/top_level.txt
piper_sdk-0.5.0.dist-info/RECORD
