Metadata-Version: 2.1
Name: piper-sdk
Version: 0.5.0
Summary: A sdk to control Agilex piper arm
Home-page: https://github.com/agilexrobotics/piper_sdk
Author: Agilex Robotice Co., Ltd.
Author-email: 
License: MIT License
Project-URL: Repository, https://github.com/agilexrobotics/piper_sdk
Project-URL: ChangeLog, https://github.com/agilexrobotics/piper_sdk/blob/master/CHANGELOG.MD
Platform: Linux
Classifier: License :: OSI Approved :: MIT License
Classifier: Programming Language :: Python :: 3.6
Classifier: Operating System :: OS Independent
Requires-Python: >=3.6
License-File: LICENSE
Requires-Dist: python-can (>=3.3.4)
